{
"type": "FeatureCollection",
"name": "Sports",
"crs": { "type": "name", "properties": { "name": "urn:ogc:def:crs:OGC:1.3:CRS84" } },
"features": [
{ "type": "Feature", "properties": { }, "geometry": { "type": "Point", "coordinates": [ -79.795571488891838, 45.359493313704746 ] } }
]
}
