{
"type": "FeatureCollection",
"name": "Swim",
"crs": { "type": "name", "properties": { "name": "urn:ogc:def:crs:OGC:1.3:CRS84" } },
"features": [
{ "type": "Feature", "properties": { }, "geometry": { "type": "Point", "coordinates": [ -79.793459829700765, 45.361175858355892 ] } }
]
}
