{
"type": "FeatureCollection",
"name": "Tennis",
"crs": { "type": "name", "properties": { "name": "urn:ogc:def:crs:OGC:1.3:CRS84" } },
"features": [
{ "type": "Feature", "properties": { }, "geometry": { "type": "Point", "coordinates": [ -79.793355078873986, 45.360087644268368 ] } }
]
}
